{
  "meta": {
    "description": "Crypto perpetual futures funding rates aggregated from Binance, Bybit, and OKX",
    "updated_utc": "2026-07-04T16:58:49.180053+00:00",
    "sources": [
      "Binance",
      "Bybit",
      "OKX"
    ],
    "symbols": [
      "BTC",
      "ETH",
      "SOL",
      "BNB",
      "XRP",
      "DOGE",
      "AVAX",
      "LINK",
      "ARB",
      "OP"
    ],
    "note": "Rates shown as percentages. Updated every run."
  },
  "data": [
    {
      "asset": "BTC",
      "exchange": "OKX",
      "rate_%": 0.006281,
      "next_funding": "00:00 UTC",
      "fetched_at": "2026-07-04T16:58:46.710654+00:00",
      "signal": "\u26aa NORMAL",
      "spread_%": null
    },
    {
      "asset": "ETH",
      "exchange": "OKX",
      "rate_%": 0.00601,
      "next_funding": "00:00 UTC",
      "fetched_at": "2026-07-04T16:58:46.964678+00:00",
      "signal": "\u26aa NORMAL",
      "spread_%": null
    },
    {
      "asset": "SOL",
      "exchange": "OKX",
      "rate_%": 0.004817,
      "next_funding": "00:00 UTC",
      "fetched_at": "2026-07-04T16:58:47.237457+00:00",
      "signal": "\u26aa NORMAL",
      "spread_%": null
    },
    {
      "asset": "BNB",
      "exchange": "OKX",
      "rate_%": 0.006369,
      "next_funding": "00:00 UTC",
      "fetched_at": "2026-07-04T16:58:47.514269+00:00",
      "signal": "\u26aa NORMAL",
      "spread_%": null
    },
    {
      "asset": "XRP",
      "exchange": "OKX",
      "rate_%": 0.005836,
      "next_funding": "00:00 UTC",
      "fetched_at": "2026-07-04T16:58:47.792381+00:00",
      "signal": "\u26aa NORMAL",
      "spread_%": null
    },
    {
      "asset": "DOGE",
      "exchange": "OKX",
      "rate_%": 0.008599,
      "next_funding": "00:00 UTC",
      "fetched_at": "2026-07-04T16:58:48.063615+00:00",
      "signal": "\u26aa NORMAL",
      "spread_%": null
    },
    {
      "asset": "AVAX",
      "exchange": "OKX",
      "rate_%": 0.01,
      "next_funding": "00:00 UTC",
      "fetched_at": "2026-07-04T16:58:48.331241+00:00",
      "signal": "\u26aa NORMAL",
      "spread_%": null
    },
    {
      "asset": "LINK",
      "exchange": "OKX",
      "rate_%": 0.01,
      "next_funding": "00:00 UTC",
      "fetched_at": "2026-07-04T16:58:48.606745+00:00",
      "signal": "\u26aa NORMAL",
      "spread_%": null
    },
    {
      "asset": "ARB",
      "exchange": "OKX",
      "rate_%": 0.005895,
      "next_funding": "00:00 UTC",
      "fetched_at": "2026-07-04T16:58:48.884385+00:00",
      "signal": "\u26aa NORMAL",
      "spread_%": null
    },
    {
      "asset": "OP",
      "exchange": "OKX",
      "rate_%": 0.01,
      "next_funding": "00:00 UTC",
      "fetched_at": "2026-07-04T16:58:49.169863+00:00",
      "signal": "\u26aa NORMAL",
      "spread_%": null
    }
  ]
}