{
  "meta": {
    "description": "Crypto perpetual futures funding rates aggregated from Binance, Bybit, and OKX",
    "updated_utc": "2026-06-17T16:35:30.348996+00:00",
    "sources": [
      "Binance",
      "Bybit",
      "OKX"
    ],
    "symbols": [
      "BTC",
      "ETH",
      "SOL",
      "BNB",
      "XRP",
      "DOGE",
      "AVAX",
      "LINK",
      "ARB",
      "OP"
    ],
    "note": "Rates shown as percentages. Updated every run."
  },
  "data": [
    {
      "asset": "BTC",
      "exchange": "OKX",
      "rate_%": -0.002744,
      "next_funding": "00:00 UTC",
      "fetched_at": "2026-06-17T16:35:28.193512+00:00",
      "signal": "\u26aa NORMAL",
      "spread_%": null
    },
    {
      "asset": "ETH",
      "exchange": "OKX",
      "rate_%": -0.001734,
      "next_funding": "00:00 UTC",
      "fetched_at": "2026-06-17T16:35:28.430242+00:00",
      "signal": "\u26aa NORMAL",
      "spread_%": null
    },
    {
      "asset": "SOL",
      "exchange": "OKX",
      "rate_%": -0.002763,
      "next_funding": "00:00 UTC",
      "fetched_at": "2026-06-17T16:35:28.654695+00:00",
      "signal": "\u26aa NORMAL",
      "spread_%": null
    },
    {
      "asset": "BNB",
      "exchange": "OKX",
      "rate_%": 0.01,
      "next_funding": "00:00 UTC",
      "fetched_at": "2026-06-17T16:35:28.914748+00:00",
      "signal": "\u26aa NORMAL",
      "spread_%": null
    },
    {
      "asset": "XRP",
      "exchange": "OKX",
      "rate_%": -0.000209,
      "next_funding": "00:00 UTC",
      "fetched_at": "2026-06-17T16:35:29.139415+00:00",
      "signal": "\u26aa NORMAL",
      "spread_%": null
    },
    {
      "asset": "DOGE",
      "exchange": "OKX",
      "rate_%": -0.008602,
      "next_funding": "00:00 UTC",
      "fetched_at": "2026-06-17T16:35:29.417638+00:00",
      "signal": "\u26aa NORMAL",
      "spread_%": null
    },
    {
      "asset": "AVAX",
      "exchange": "OKX",
      "rate_%": 0.005169,
      "next_funding": "00:00 UTC",
      "fetched_at": "2026-06-17T16:35:29.644175+00:00",
      "signal": "\u26aa NORMAL",
      "spread_%": null
    },
    {
      "asset": "LINK",
      "exchange": "OKX",
      "rate_%": 0.01,
      "next_funding": "00:00 UTC",
      "fetched_at": "2026-06-17T16:35:29.865283+00:00",
      "signal": "\u26aa NORMAL",
      "spread_%": null
    },
    {
      "asset": "ARB",
      "exchange": "OKX",
      "rate_%": 0.009737,
      "next_funding": "00:00 UTC",
      "fetched_at": "2026-06-17T16:35:30.104296+00:00",
      "signal": "\u26aa NORMAL",
      "spread_%": null
    },
    {
      "asset": "OP",
      "exchange": "OKX",
      "rate_%": -0.006986,
      "next_funding": "00:00 UTC",
      "fetched_at": "2026-06-17T16:35:30.337791+00:00",
      "signal": "\u26aa NORMAL",
      "spread_%": null
    }
  ]
}