{
  "meta": {
    "description": "Crypto perpetual futures funding rates aggregated from Binance, Bybit, and OKX",
    "updated_utc": "2026-07-03T19:11:15.261517+00:00",
    "sources": [
      "Binance",
      "Bybit",
      "OKX"
    ],
    "symbols": [
      "BTC",
      "ETH",
      "SOL",
      "BNB",
      "XRP",
      "DOGE",
      "AVAX",
      "LINK",
      "ARB",
      "OP"
    ],
    "note": "Rates shown as percentages. Updated every run."
  },
  "data": [
    {
      "asset": "BTC",
      "exchange": "OKX",
      "rate_%": 0.004215,
      "next_funding": "00:00 UTC",
      "fetched_at": "2026-07-03T19:11:13.508190+00:00",
      "signal": "\u26aa NORMAL",
      "spread_%": null
    },
    {
      "asset": "ETH",
      "exchange": "OKX",
      "rate_%": 0.006065,
      "next_funding": "00:00 UTC",
      "fetched_at": "2026-07-03T19:11:13.700315+00:00",
      "signal": "\u26aa NORMAL",
      "spread_%": null
    },
    {
      "asset": "SOL",
      "exchange": "OKX",
      "rate_%": 0.007497,
      "next_funding": "00:00 UTC",
      "fetched_at": "2026-07-03T19:11:13.895675+00:00",
      "signal": "\u26aa NORMAL",
      "spread_%": null
    },
    {
      "asset": "BNB",
      "exchange": "OKX",
      "rate_%": 0.01,
      "next_funding": "00:00 UTC",
      "fetched_at": "2026-07-03T19:11:14.090748+00:00",
      "signal": "\u26aa NORMAL",
      "spread_%": null
    },
    {
      "asset": "XRP",
      "exchange": "OKX",
      "rate_%": 0.01,
      "next_funding": "00:00 UTC",
      "fetched_at": "2026-07-03T19:11:14.283028+00:00",
      "signal": "\u26aa NORMAL",
      "spread_%": null
    },
    {
      "asset": "DOGE",
      "exchange": "OKX",
      "rate_%": 0.01,
      "next_funding": "00:00 UTC",
      "fetched_at": "2026-07-03T19:11:14.483482+00:00",
      "signal": "\u26aa NORMAL",
      "spread_%": null
    },
    {
      "asset": "AVAX",
      "exchange": "OKX",
      "rate_%": -0.005915,
      "next_funding": "00:00 UTC",
      "fetched_at": "2026-07-03T19:11:14.674536+00:00",
      "signal": "\u26aa NORMAL",
      "spread_%": null
    },
    {
      "asset": "LINK",
      "exchange": "OKX",
      "rate_%": 0.01,
      "next_funding": "00:00 UTC",
      "fetched_at": "2026-07-03T19:11:14.861353+00:00",
      "signal": "\u26aa NORMAL",
      "spread_%": null
    },
    {
      "asset": "ARB",
      "exchange": "OKX",
      "rate_%": 0.009386,
      "next_funding": "00:00 UTC",
      "fetched_at": "2026-07-03T19:11:15.056606+00:00",
      "signal": "\u26aa NORMAL",
      "spread_%": null
    },
    {
      "asset": "OP",
      "exchange": "OKX",
      "rate_%": 0.01,
      "next_funding": "00:00 UTC",
      "fetched_at": "2026-07-03T19:11:15.250824+00:00",
      "signal": "\u26aa NORMAL",
      "spread_%": null
    }
  ]
}