{
  "meta": {
    "description": "Crypto perpetual futures funding rates aggregated from Binance, Bybit, and OKX",
    "updated_utc": "2026-05-26T19:29:23.494440+00:00",
    "sources": [
      "Binance",
      "Bybit",
      "OKX"
    ],
    "symbols": [
      "BTC",
      "ETH",
      "SOL",
      "BNB",
      "XRP",
      "DOGE",
      "AVAX",
      "LINK",
      "ARB",
      "OP"
    ],
    "note": "Rates shown as percentages. Updated every run."
  },
  "data": [
    {
      "asset": "BTC",
      "exchange": "OKX",
      "rate_%": 0.009631,
      "next_funding": "00:00 UTC",
      "fetched_at": "2026-05-26T19:29:21.011993+00:00",
      "signal": "\u26aa NORMAL",
      "spread_%": null
    },
    {
      "asset": "ETH",
      "exchange": "OKX",
      "rate_%": 0.003997,
      "next_funding": "00:00 UTC",
      "fetched_at": "2026-05-26T19:29:21.271168+00:00",
      "signal": "\u26aa NORMAL",
      "spread_%": null
    },
    {
      "asset": "SOL",
      "exchange": "OKX",
      "rate_%": -0.008769,
      "next_funding": "00:00 UTC",
      "fetched_at": "2026-05-26T19:29:21.567062+00:00",
      "signal": "\u26aa NORMAL",
      "spread_%": null
    },
    {
      "asset": "BNB",
      "exchange": "OKX",
      "rate_%": -0.001927,
      "next_funding": "00:00 UTC",
      "fetched_at": "2026-05-26T19:29:21.847457+00:00",
      "signal": "\u26aa NORMAL",
      "spread_%": null
    },
    {
      "asset": "XRP",
      "exchange": "OKX",
      "rate_%": -0.011929,
      "next_funding": "00:00 UTC",
      "fetched_at": "2026-05-26T19:29:22.128304+00:00",
      "signal": "\ud83d\udd35 LOW NEGATIVE",
      "spread_%": null
    },
    {
      "asset": "DOGE",
      "exchange": "OKX",
      "rate_%": -0.004743,
      "next_funding": "00:00 UTC",
      "fetched_at": "2026-05-26T19:29:22.388444+00:00",
      "signal": "\u26aa NORMAL",
      "spread_%": null
    },
    {
      "asset": "AVAX",
      "exchange": "OKX",
      "rate_%": -0.002186,
      "next_funding": "00:00 UTC",
      "fetched_at": "2026-05-26T19:29:22.668104+00:00",
      "signal": "\u26aa NORMAL",
      "spread_%": null
    },
    {
      "asset": "LINK",
      "exchange": "OKX",
      "rate_%": 0.009767,
      "next_funding": "00:00 UTC",
      "fetched_at": "2026-05-26T19:29:22.938655+00:00",
      "signal": "\u26aa NORMAL",
      "spread_%": null
    },
    {
      "asset": "ARB",
      "exchange": "OKX",
      "rate_%": -0.010823,
      "next_funding": "00:00 UTC",
      "fetched_at": "2026-05-26T19:29:23.213685+00:00",
      "signal": "\ud83d\udd35 LOW NEGATIVE",
      "spread_%": null
    },
    {
      "asset": "OP",
      "exchange": "OKX",
      "rate_%": 0.01,
      "next_funding": "00:00 UTC",
      "fetched_at": "2026-05-26T19:29:23.483901+00:00",
      "signal": "\u26aa NORMAL",
      "spread_%": null
    }
  ]
}