{
  "meta": {
    "description": "Crypto perpetual futures funding rates aggregated from Binance, Bybit, and OKX",
    "updated_utc": "2026-07-17T05:36:04.769775+00:00",
    "sources": [
      "Binance",
      "Bybit",
      "OKX"
    ],
    "symbols": [
      "BTC",
      "ETH",
      "SOL",
      "BNB",
      "XRP",
      "DOGE",
      "AVAX",
      "LINK",
      "ARB",
      "OP"
    ],
    "note": "Rates shown as percentages. Updated every run."
  },
  "data": [
    {
      "asset": "BTC",
      "exchange": "OKX",
      "rate_%": 0.005006,
      "next_funding": "08:00 UTC",
      "fetched_at": "2026-07-17T05:36:02.682914+00:00",
      "signal": "\u26aa NORMAL",
      "spread_%": null
    },
    {
      "asset": "ETH",
      "exchange": "OKX",
      "rate_%": 0.007839,
      "next_funding": "08:00 UTC",
      "fetched_at": "2026-07-17T05:36:02.927467+00:00",
      "signal": "\u26aa NORMAL",
      "spread_%": null
    },
    {
      "asset": "SOL",
      "exchange": "OKX",
      "rate_%": 0.005112,
      "next_funding": "08:00 UTC",
      "fetched_at": "2026-07-17T05:36:03.156298+00:00",
      "signal": "\u26aa NORMAL",
      "spread_%": null
    },
    {
      "asset": "BNB",
      "exchange": "OKX",
      "rate_%": -0.001226,
      "next_funding": "08:00 UTC",
      "fetched_at": "2026-07-17T05:36:03.383579+00:00",
      "signal": "\u26aa NORMAL",
      "spread_%": null
    },
    {
      "asset": "XRP",
      "exchange": "OKX",
      "rate_%": 0.01,
      "next_funding": "08:00 UTC",
      "fetched_at": "2026-07-17T05:36:03.612878+00:00",
      "signal": "\u26aa NORMAL",
      "spread_%": null
    },
    {
      "asset": "DOGE",
      "exchange": "OKX",
      "rate_%": 0.004695,
      "next_funding": "08:00 UTC",
      "fetched_at": "2026-07-17T05:36:03.843055+00:00",
      "signal": "\u26aa NORMAL",
      "spread_%": null
    },
    {
      "asset": "AVAX",
      "exchange": "OKX",
      "rate_%": -0.002543,
      "next_funding": "08:00 UTC",
      "fetched_at": "2026-07-17T05:36:04.071985+00:00",
      "signal": "\u26aa NORMAL",
      "spread_%": null
    },
    {
      "asset": "LINK",
      "exchange": "OKX",
      "rate_%": -0.000338,
      "next_funding": "08:00 UTC",
      "fetched_at": "2026-07-17T05:36:04.294111+00:00",
      "signal": "\u26aa NORMAL",
      "spread_%": null
    },
    {
      "asset": "ARB",
      "exchange": "OKX",
      "rate_%": -0.006041,
      "next_funding": "08:00 UTC",
      "fetched_at": "2026-07-17T05:36:04.525224+00:00",
      "signal": "\u26aa NORMAL",
      "spread_%": null
    },
    {
      "asset": "OP",
      "exchange": "OKX",
      "rate_%": -0.0388,
      "next_funding": "08:00 UTC",
      "fetched_at": "2026-07-17T05:36:04.758613+00:00",
      "signal": "\ud83d\udd35 LOW NEGATIVE",
      "spread_%": null
    }
  ]
}